[
  {
    "email": "alejandro.alvaradorojas@usc.edu",
    "name": "Alejandro Alvarado Rojas",
    "school": "USC Annenberg School for Communication and Journalism",
    "program": "Communication PhD"
  },
  {
    "email": "ljarnold@usc.edu",
    "name": "Lauren Jade Arnold",
    "school": "USC Annenberg School for Communication and Journalism",
    "program": "Communication PhD"
  },
  {
    "email": "sashtari@usc.edu",
    "name": "Shadee Ashtari",
    "school": "USC Annenberg School for Communication and Journalism",
    "program": "Communication PhD"
  },
  {
    "email": "zbbadr@usc.edu",
    "name": "Zahraa Badr",
    "school": "USC Annenberg School for Communication and Journalism",
    "program": "Communication PhD"
  },
  {
    "email": "abbaird@usc.edu",
    "name": "Ash Baird",
    "school": "USC Annenberg School for Communication and Journalism",
    "program": "Communication PhD"
  },
  {
    "email": "rakabhat@usc.edu",
    "name": "Raka Bhattacharyya",
    "school": "USC Annenberg School for Communication and Journalism",
    "program": "Communication PhD"
  },
  {
    "email": "caolei@usc.edu",
    "name": "Lei Cao",
    "school": "USC Annenberg School for Communication and Journalism",
    "program": "Communication PhD"
  },
  {
    "email": "euncheol@usc.edu",
    "name": "Eun Cheol Choi",
    "school": "USC Annenberg School for Communication and Journalism",
    "program": "Communication PhD"
  },
  {
    "email": "kcrowe@usc.edu",
    "name": "Kirsten Crowe",
    "school": "USC Annenberg School for Communication and Journalism",
    "program": "Communication PhD"
  },
  {
    "email": "magcurry@usc.edu",
    "name": "Magdalayna Curry",
    "school": "USC Annenberg School for Communication and Journalism",
    "program": "Communication PhD"
  },
  {
    "email": "dadoolom@usc.edu",
    "name": "Vita Dadoo",
    "school": "USC Annenberg School for Communication and Journalism",
    "program": "Communication PhD"
  },
  {
    "email": "aridavid@usc.edu",
    "name": "Ari Davidson",
    "school": "USC Annenberg School for Communication and Journalism",
    "program": "Communication PhD"
  },
  {
    "email": "katrinfi@usc.edu",
    "name": "Katrin Fischer",
    "school": "USC Annenberg School for Communication and Journalism",
    "program": "Communication PhD"
  },
  {
    "email": "mfrizzel@usc.edu",
    "name": "Molly Frizzell",
    "school": "USC Annenberg School for Communication and Journalism",
    "program": "Communication PhD"
  },
  {
    "email": "yvonne.gonzales@usc.edu",
    "name": "Yvonne Gonzales",
    "school": "USC Annenberg School for Communication and Journalism",
    "program": "Communication PhD"
  },
  {
    "email": "haytin@usc.edu",
    "name": "Sofia Haytin",
    "school": "USC Annenberg School for Communication and Journalism",
    "program": "Communication PhD"
  },
  {
    "email": "akhegde@usc.edu",
    "name": "Alfonso Hegde",
    "school": "USC Annenberg School for Communication and Journalism",
    "program": "Communication PhD"
  },
  {
    "email": "edithhol@usc.edu",
    "name": "Edith Hollander",
    "school": "USC Annenberg School for Communication and Journalism",
    "program": "Communication PhD"
  },
  {
    "email": "huangish@usc.edu",
    "name": "Ke (Maddie) Huang-Isherwood",
    "school": "USC Annenberg School for Communication and Journalism",
    "program": "Communication PhD"
  },
  {
    "email": "kyooeunj@usc.edu",
    "name": "Kyooeun Jang",
    "school": "USC Annenberg School for Communication and Journalism",
    "program": "Communication PhD"
  },
  {
    "email": "elaine.jeon@usc.edu",
    "name": "Elaine Jeon",
    "school": "USC Annenberg School for Communication and Journalism",
    "program": "Communication PhD"
  },
  {
    "email": "muyaojia@usc.edu",
    "name": "Muyao Jiang",
    "school": "USC Annenberg School for Communication and Journalism",
    "program": "Communication PhD"
  },
  {
    "email": "bumju.jung@usc.edu",
    "name": "Bumju Jung",
    "school": "USC Annenberg School for Communication and Journalism",
    "program": "Communication PhD"
  },
  {
    "email": "kentdani@usc.edu",
    "name": "Daniela Kent",
    "school": "USC Annenberg School for Communication and Journalism",
    "program": "Communication PhD"
  },
  {
    "email": "doheekim@usc.edu",
    "name": "Dohee Kim",
    "school": "USC Annenberg School for Communication and Journalism",
    "program": "Communication PhD"
  },
  {
    "email": "jiyek@usc.edu",
    "name": "Ji Ye Kim",
    "school": "USC Annenberg School for Communication and Journalism",
    "program": "Communication PhD"
  },
  {
    "email": "donggyuk@usc.edu",
    "name": "Donggyu Kim",
    "school": "USC Annenberg School for Communication and Journalism",
    "program": "Communication PhD"
  },
  {
    "email": "garyeung@usc.edu",
    "name": "Natalie Kim",
    "school": "USC Annenberg School for Communication and Journalism",
    "program": "Communication PhD"
  },
  {
    "email": "grking@usc.edu",
    "name": "Glenn King",
    "school": "USC Annenberg School for Communication and Journalism",
    "program": "Communication PhD"
  },
  {
    "email": "lanzgarc@usc.edu",
    "name": "Paulina Lanz",
    "school": "USC Annenberg School for Communication and Journalism",
    "program": "Communication PhD"
  },
  {
    "email": "mleccese@usc.edu",
    "name": "Michelle Leccese",
    "school": "USC Annenberg School for Communication and Journalism",
    "program": "Communication PhD"
  },
  {
    "email": "hyerilee@usc.edu",
    "name": "Hyeri Lee",
    "school": "USC Annenberg School for Communication and Journalism",
    "program": "Communication PhD"
  },
  {
    "email": "seongkyu@usc.edu",
    "name": "Seongkyung Lee",
    "school": "USC Annenberg School for Communication and Journalism",
    "program": "Communication PhD"
  },
  {
    "email": "fionali@usc.edu",
    "name": "Fiona Li",
    "school": "USC Annenberg School for Communication and Journalism",
    "program": "Communication PhD"
  },
  {
    "email": "kexinlin@usc.edu",
    "name": "Stella Lin",
    "school": "USC Annenberg School for Communication and Journalism",
    "program": "Communication PhD"
  },
  {
    "email": "fylu@usc.edu",
    "name": "Felicia Lu",
    "school": "USC Annenberg School for Communication and Journalism",
    "program": "Communication PhD"
  },
  {
    "email": "lyamuya@usc.edu",
    "name": "Alphoncina (Allie) Lyamuya",
    "school": "USC Annenberg School for Communication and Journalism",
    "program": "Communication PhD"
  },
  {
    "email": "shufan@usc.edu",
    "name": "Shufan Mao",
    "school": "USC Annenberg School for Communication and Journalism",
    "program": "Communication PhD"
  },
  {
    "email": "rjmichae@usc.edu",
    "name": "Joshua Michael",
    "school": "USC Annenberg School for Communication and Journalism",
    "program": "Communication PhD"
  },
  {
    "email": "nyaupane@usc.edu",
    "name": "Pratik Nyaupane",
    "school": "USC Annenberg School for Communication and Journalism",
    "program": "Communication PhD"
  },
  {
    "email": "orrw@usc.edu",
    "name": "Will Orr",
    "school": "USC Annenberg School for Communication and Journalism",
    "program": "Communication PhD"
  },
  {
    "email": "ortizfre@usc.edu",
    "name": "Juan Ortiz Freuler",
    "school": "USC Annenberg School for Communication and Journalism",
    "program": "Communication PhD"
  },
  {
    "email": "jpanalig@usc.edu",
    "name": "Joy Hannah Panaligan",
    "school": "USC Annenberg School for Communication and Journalism",
    "program": "Communication PhD"
  },
  {
    "email": "sproudfo@usc.edu",
    "name": "Steven Proudfoot",
    "school": "USC Annenberg School for Communication and Journalism",
    "program": "Communication PhD"
  },
  {
    "email": "apuzon@usc.edu",
    "name": "Alicia Gabrielle Puzon",
    "school": "USC Annenberg School for Communication and Journalism",
    "program": "Communication PhD"
  },
  {
    "email": "jramos59@usc.edu",
    "name": "Jessica Ramos",
    "school": "USC Annenberg School for Communication and Journalism",
    "program": "Communication PhD"
  },
  {
    "email": "jermaine.richards@usc.edu",
    "name": "Jermaine Anthony Richards",
    "school": "USC Annenberg School for Communication and Journalism",
    "program": "Communication PhD"
  },
  {
    "email": "javierri@usc.edu",
    "name": "Javier Rivera",
    "school": "USC Annenberg School for Communication and Journalism",
    "program": "Communication PhD"
  },
  {
    "email": "sadig@usc.edu",
    "name": "Samah Sadig",
    "school": "USC Annenberg School for Communication and Journalism",
    "program": "Communication PhD"
  },
  {
    "email": "nsafi@usc.edu",
    "name": "Nitanga Yvoni Safi",
    "school": "USC Annenberg School for Communication and Journalism",
    "program": "Communication PhD"
  },
  {
    "email": "tzsen@usc.edu",
    "name": "Tuğba Sen",
    "school": "USC Annenberg School for Communication and Journalism",
    "program": "Communication PhD"
  },
  {
    "email": "rylandsh@usc.edu",
    "name": "Ryland Shaw",
    "school": "USC Annenberg School for Communication and Journalism",
    "program": "Communication PhD"
  },
  {
    "email": "soriacru@usc.edu",
    "name": "Fernanda Soria",
    "school": "USC Annenberg School for Communication and Journalism",
    "program": "Communication PhD"
  },
  {
    "email": "hamsinis@usc.edu",
    "name": "Hamsini Sridharan",
    "school": "USC Annenberg School for Communication and Journalism",
    "program": "Communication PhD"
  },
  {
    "email": "stecson@usc.edu",
    "name": "Samantha Tecson",
    "school": "USC Annenberg School for Communication and Journalism",
    "program": "Communication PhD"
  },
  {
    "email": "dnthomas@usc.edu",
    "name": "nikki thomas",
    "school": "USC Annenberg School for Communication and Journalism",
    "program": "Communication PhD"
  },
  {
    "email": "dtoor@usc.edu",
    "name": "Denise Dilbir Kaur Toor",
    "school": "USC Annenberg School for Communication and Journalism",
    "program": "Communication PhD"
  },
  {
    "email": "zituowan@usc.edu",
    "name": "Zituo Wang",
    "school": "USC Annenberg School for Communication and Journalism",
    "program": "Communication PhD"
  },
  {
    "email": "suiwang@usc.edu",
    "name": "Sui Wang",
    "school": "USC Annenberg School for Communication and Journalism",
    "program": "Communication PhD"
  },
  {
    "email": "ywang965@usc.edu",
    "name": "Ying Wang",
    "school": "USC Annenberg School for Communication and Journalism",
    "program": "Communication PhD"
  },
  {
    "email": "jwidera@usc.edu",
    "name": "Josh Widera",
    "school": "USC Annenberg School for Communication and Journalism",
    "program": "Communication PhD"
  },
  {
    "email": "louisexi@usc.edu",
    "name": "Louise Xie",
    "school": "USC Annenberg School for Communication and Journalism",
    "program": "Communication PhD"
  },
  {
    "email": "stepheny@usc.edu",
    "name": "Stephen Yang",
    "school": "USC Annenberg School for Communication and Journalism",
    "program": "Communication PhD"
  },
  {
    "email": "yyang418@usc.edu",
    "name": "Yuqi Yang",
    "school": "USC Annenberg School for Communication and Journalism",
    "program": "Communication PhD"
  },
  {
    "email": "jzhai562@usc.edu",
    "name": "Jiaying (Vivian) Zhai",
    "school": "USC Annenberg School for Communication and Journalism",
    "program": "Communication PhD"
  },
  {
    "email": "zhousiyi@usc.edu",
    "name": "Siyi Zhou",
    "school": "USC Annenberg School for Communication and Journalism",
    "program": "Communication PhD"
  },
  {
    "email": "kedizhou@usc.edu",
    "name": "Kedi Zhou",
    "school": "USC Annenberg School for Communication and Journalism",
    "program": "Communication PhD"
  },
  {
    "email": "jimmyagu@usc.edu",
    "name": "Jimmy  Aguilar",
    "school": "USC Rossier School of Education",
    "program": "PhD - Higher Education"
  },
  {
    "email": "jacob.alonso@usc.edu",
    "name": "Jacob  Alonso",
    "school": "USC Rossier School of Education",
    "program": "PhD - K-12 Education Policy"
  },
  {
    "email": "anglon@usc.edu",
    "name": "Gloria C. Anglón",
    "school": "USC Rossier School of Education",
    "program": "PhD - Higher Education"
  },
  {
    "email": "junminby@usc.edu",
    "name": "Junmin  Byon",
    "school": "USC Rossier School of Education",
    "program": "PhD - K-12 Education Policy"
  },
  {
    "email": "lcarranza@usc.edu",
    "name": "Jessica Leila  Carranza",
    "school": "USC Rossier School of Education",
    "program": "PhD - K-12 Education Policy"
  },
  {
    "email": "chunghye@usc.edu",
    "name": "Julie  Chung",
    "school": "USC Rossier School of Education",
    "program": "PhD - Educational Psychology"
  },
  {
    "email": "iclay@usc.edu",
    "name": "Isabel  Clay",
    "school": "USC Rossier School of Education",
    "program": "PhD - K-12 Education Policy"
  },
  {
    "email": "dawsonam@usc.edu",
    "name": "Margaret  Dawson-Amoah, Miss",
    "school": "USC Rossier School of Education",
    "program": "PhD - K-12 Education Policy"
  },
  {
    "email": "aducharm@usc.edu",
    "name": "Alden R. B. Ducharme",
    "school": "USC Rossier School of Education",
    "program": "PhD - Teacher Education"
  },
  {
    "email": "daniele8@usc.edu",
    "name": "Daniel  Espinoza",
    "school": "USC Rossier School of Education",
    "program": "PhD - K-12 Education Policy"
  },
  {
    "email": "emilyg@usc.edu",
    "name": "Emily  Gonzalez",
    "school": "USC Rossier School of Education",
    "program": "PhD - Educational Psychology"
  },
  {
    "email": "jgribben@usc.edu",
    "name": "Jennifer  Gribben",
    "school": "USC Rossier School of Education",
    "program": "PhD - Educational Psychology"
  },
  {
    "email": "mgrigsby@usc.edu",
    "name": "Michael  Grigsby",
    "school": "USC Rossier School of Education",
    "program": "PhD - Higher Education"
  },
  {
    "email": "keenajon@usc.edu",
    "name": "Keena  Jones",
    "school": "USC Rossier School of Education",
    "program": "PhD - Educational Psychology"
  },
  {
    "email": "reinak@usc.edu",
    "name": "Reina  Kang",
    "school": "USC Rossier School of Education",
    "program": "PhD - Educational Psychology"
  },
  {
    "email": "aleach@usc.edu",
    "name": "Ashley  Leach",
    "school": "USC Rossier School of Education",
    "program": "PhD - Educational Psychology"
  },
  {
    "email": "andreajm@usc.edu",
    "name": "Andrea Jackelyn Macias",
    "school": "USC Rossier School of Education",
    "program": "PhD - Educational Psychology"
  },
  {
    "email": "makori@usc.edu",
    "name": "Alvin  Makori",
    "school": "USC Rossier School of Education",
    "program": "PhD - K-12 Education Policy"
  },
  {
    "email": "gpduran@usc.edu",
    "name": "Marcus Maximus Martin",
    "school": "USC Rossier School of Education",
    "program": "PhD - Higher Education"
  },
  {
    "email": "smodares@usc.edu",
    "name": "Saba Lily Modaressi",
    "school": "USC Rossier School of Education",
    "program": "PhD - Educational Psychology"
  },
  {
    "email": "kamoreno@usc.edu",
    "name": "Kyle  Moreno",
    "school": "USC Rossier School of Education",
    "program": "PhD - Teacher Education"
  },
  {
    "email": "morrisel@usc.edu",
    "name": "Elizabeth (Liddy) Morris",
    "school": "USC Rossier School of Education",
    "program": "PhD - K-12 Education Policy"
  },
  {
    "email": "dloneal@usc.edu",
    "name": "Desiree  O'Neal",
    "school": "USC Rossier School of Education",
    "program": "PhD - K-12 Education Policy"
  },
  {
    "email": "aoduro@usc.edu",
    "name": "Alexia  Oduro",
    "school": "USC Rossier School of Education",
    "program": "PhD - Higher Education"
  },
  {
    "email": "oterogut@usc.edu",
    "name": "Salomé  Otero",
    "school": "USC Rossier School of Education",
    "program": "PhD - Higher Education"
  },
  {
    "email": "glendapa@usc.edu",
    "name": "Glenda  Palacios Quejada",
    "school": "USC Rossier School of Education",
    "program": "PhD - Higher Education"
  },
  {
    "email": "rabovsky@usc.edu",
    "name": "Sarah  Rabovsky",
    "school": "USC Rossier School of Education",
    "program": "PhD - K-12 Education Policy"
  },
  {
    "email": "janetriv@usc.edu",
    "name": "Janet  Rivera",
    "school": "USC Rossier School of Education",
    "program": "PhD - Higher Education"
  },
  {
    "email": "scollanr@usc.edu",
    "name": "Jake  Scollan-Rowley",
    "school": "USC Rossier School of Education",
    "program": "PhD - K-12 Education Policy"
  },
  {
    "email": "dsilvagg@usc.edu",
    "name": "Danielle  Silvaggio",
    "school": "USC Rossier School of Education",
    "program": "PhD - Teacher Education"
  },
  {
    "email": "shelbysm@usc.edu",
    "name": "Shelby Leigh Smith",
    "school": "USC Rossier School of Education",
    "program": "PhD - K-12 Education Policy"
  },
  {
    "email": "ttong059@usc.edu",
    "name": "Tong  Tong",
    "school": "USC Rossier School of Education",
    "program": "PhD - K-12 Education Policy"
  },
  {
    "email": "torr943@usc.edu",
    "name": "Gabriela  Torres",
    "school": "USC Rossier School of Education",
    "program": "PhD - Higher Education"
  },
  {
    "email": "uka@usc.edu",
    "name": "Akunna Faith Uka",
    "school": "USC Rossier School of Education",
    "program": "PhD - K-12 Education Policy"
  },
  {
    "email": "wangsiha@usc.edu",
    "name": "Sihan (Jen)  Wang",
    "school": "USC Rossier School of Education",
    "program": "PhD - Educational Psychology"
  },
  {
    "email": "xingyuqi@usc.edu",
    "name": "Yuqing Kyra  Xing",
    "school": "USC Rossier School of Education",
    "program": "PhD - Educational Psychology"
  },
  {
    "email": "lxiu@usc.edu",
    "name": "Le Rosie Xiu",
    "school": "USC Rossier School of Education",
    "program": "PhD - Educational Psychology"
  },
  {
    "email": "yanyanzo@usc.edu",
    "name": "Yanyan  Zong",
    "school": "USC Rossier School of Education",
    "program": "PhD - Educational Psychology"
  },
  {
    "email": "dbaid@usc.edu",
    "name": "Drishti Baid",
    "school": "USC Price School of Public Policy",
    "program": "PhD in Public Policy and Management"
  },
  {
    "email": "elizab@usc.edu",
    "name": "Eliza Bennett",
    "school": "USC Price School of Public Policy",
    "program": "PhD in Public Policy and Management"
  },
  {
    "email": "aibarton@usc.edu",
    "name": "Andrew Barton",
    "school": "USC Price School of Public Policy",
    "program": "PhD in Public Policy and Management"
  },
  {
    "email": "manying@usc.edu",
    "name": "Mandy Cui",
    "school": "USC Price School of Public Policy",
    "program": "PhD in Public Policy and Management"
  },
  {
    "email": "jcoutin@usc.edu",
    "name": "Brandon DeBruhl",
    "school": "USC Price School of Public Policy",
    "program": "PhD in Public Policy and Management"
  },
  {
    "email": "debruhl@usc.edu",
    "name": "Brandon DeBruhl",
    "school": "USC Price School of Public Policy",
    "program": "PhD in Public Policy and Management"
  },
  {
    "email": "estherg@usc.edu",
    "name": "Esther Gonzalez",
    "school": "USC Price School of Public Policy",
    "program": "PhD in Public Policy and Management"
  },
  {
    "email": "greavess@usc.edu",
    "name": "Jochelle Greaves Siew",
    "school": "USC Price School of Public Policy",
    "program": "PhD in Public Policy and Management"
  },
  {
    "email": "jrhendri@usc.edu",
    "name": "James Hendrickson",
    "school": "USC Price School of Public Policy",
    "program": "PhD in Public Policy and Management"
  },
  {
    "email": "shelland@usc.edu",
    "name": "Sophia Helland",
    "school": "USC Price School of Public Policy",
    "program": "PhD in Public Policy and Management"
  },
  {
    "email": "azkaimra@usc.edu",
    "name": "Azka Imran",
    "school": "USC Price School of Public Policy",
    "program": "PhD in Public Policy and Management"
  },
  {
    "email": "saumyakh@usc.edu",
    "name": "Saumya Khanna",
    "school": "USC Price School of Public Policy",
    "program": "PhD in Public Policy and Management"
  },
  {
    "email": "plee4540@usc.edu",
    "name": "Phillip Sangwoo Lee",
    "school": "USC Price School of Public Policy",
    "program": "PhD in Public Policy and Management"
  },
  {
    "email": "luxinran@usc.edu",
    "name": "Xinran (Zoey)Lu",
    "school": "USC Price School of Public Policy",
    "program": "PhD in Public Policy and Management"
  },
  {
    "email": "pradamed@usc.edu",
    "name": "Laura Prada",
    "school": "USC Price School of Public Policy",
    "program": "PhD in Public Policy and Management"
  },
  {
    "email": "Sr16724@usc.edu",
    "name": "SamanthaRandall",
    "school": "USC Price School of Public Policy",
    "program": "PhD in Public Policy and Management"
  },
  {
    "email": "micanriv@usc.edu",
    "name": "Catalina Mican-Rivera",
    "school": "USC Price School of Public Policy",
    "program": "PhD in Public Policy and Management"
  },
  {
    "email": "annsong@usc.edu",
    "name": "Ann Song",
    "school": "USC Price School of Public Policy",
    "program": "PhD in Public Policy and Management"
  },
  {
    "email": "spertus@usc.edu",
    "name": "DanielSpertus",
    "school": "USC Price School of Public Policy",
    "program": "PhD in Public Policy and Management"
  },
  {
    "email": "hbark@usc.edu",
    "name": "Hyehyeon Bark",
    "school": "USC Price School of Public Policy",
    "program": "PhD in Urban Planning and Development"
  },
  {
    "email": "rbinder@usc.edu",
    "name": "Robert Binder",
    "school": "USC Price School of Public Policy",
    "program": "PhD in Urban Planning and Development"
  },
  {
    "email": "browndes@usc.edu",
    "name": "Destiny Brown",
    "school": "USC Price School of Public Policy",
    "program": "PhD in Urban Planning and Development"
  },
  {
    "email": "ascheng@usc.edu",
    "name": "Alycia Cheng",
    "school": "USC Price School of Public Policy",
    "program": "PhD in Urban Planning and Development"
  },
  {
    "email": "rchen912@usc.edu",
    "name": "Ruoyu Chen",
    "school": "USC Price School of Public Policy",
    "program": "PhD in Urban Planning and Development"
  },
  {
    "email": "seongmoc@usc.edu",
    "name": "Seongmoon Cho",
    "school": "USC Price School of Public Policy",
    "program": "PhD in Urban Planning and Development"
  },
  {
    "email": "shdexter@usc.edu",
    "name": "Sue Dexter",
    "school": "USC Price School of Public Policy",
    "program": "PhD in Urban Planning and Development"
  },
  {
    "email": "dongjiaq@usc.edu",
    "name": "Jiaqi Dong",
    "school": "USC Price School of Public Policy",
    "program": "PhD in Urban Planning and Development"
  },
  {
    "email": "grossjam@usc.edu",
    "name": "James Gross",
    "school": "USC Price School of Public Policy",
    "program": "PhD in Urban Planning and Development"
  },
  {
    "email": "hoorijan@usc.edu",
    "name": "Nassim Hoorijani",
    "school": "USC Price School of Public Policy",
    "program": "PhD in Urban Planning and Development"
  },
  {
    "email": "kimjiyoo@usc.edu",
    "name": "Jiyoon Kim",
    "school": "USC Price School of Public Policy",
    "program": "PhD in Urban Planning and Development"
  },
  {
    "email": "jodyl@usc.edu",
    "name": "Jody Liu",
    "school": "USC Price School of Public Policy",
    "program": "PhD in Urban Planning and Development"
  },
  {
    "email": "sihanmao@usc.edu",
    "name": "Sihan Mao",
    "school": "USC Price School of Public Policy",
    "program": "PhD in Urban Planning and Development"
  },
  {
    "email": "mattoo@usc.edu",
    "name": "Saisha Mattoo",
    "school": "USC Price School of Public Policy",
    "program": "PhD in Urban Planning and Development"
  },
  {
    "email": "rosasflo@usc.edu",
    "name": "David Flores Moctezuma",
    "school": "USC Price School of Public Policy",
    "program": "PhD in Urban Planning and Development"
  },
  {
    "email": "thuanguy@usc.edu",
    "name": "Thu Nguyen",
    "school": "USC Price School of Public Policy",
    "program": "PhD in Urban Planning and Development"
  },
  {
    "email": "agoreill@usc.edu",
    "name": "Aisling O’Reilly",
    "school": "USC Price School of Public Policy",
    "program": "PhD in Urban Planning and Development"
  },
  {
    "email": "marleyra@usc.edu",
    "name": "Marley Randazzo",
    "school": "USC Price School of Public Policy",
    "program": "PhD in Urban Planning and Development"
  },
  {
    "email": "qifan.shao@usc.edu",
    "name": "Qifan Shao",
    "school": "USC Price School of Public Policy",
    "program": "PhD in Urban Planning and Development"
  },
  {
    "email": "elanarsi@usc.edu",
    "name": "Elana Simon",
    "school": "USC Price School of Public Policy",
    "program": "PhD in Urban Planning and Development"
  },
  {
    "email": "shengtan@usc.edu",
    "name": "Sheng (Christa)Tang",
    "school": "USC Price School of Public Policy",
    "program": "PhD in Urban Planning and Development"
  },
  {
    "email": "yuquanzh@usc.edu",
    "name": "Yuquan (Wendy) Zhou",
    "school": "USC Price School of Public Policy",
    "program": "PhD in Urban Planning and Development"
  },
  {
    "email": "acs@lawmail.usc.edu",
    "name": "The American Constitution Society (ACS) believes that law should be a force to improve the lives of ",
    "school": "USC Gould School of Law",
    "program": "Student Organization"
  },
  {
    "email": "alsasc@lawmail.usc.edu",
    "name": "The Armenian Law Students Association provides mentorship and networking opportunities, offers a for",
    "school": "USC Gould School of Law",
    "program": "Student Organization"
  },
  {
    "email": "aisl@lawmail.usc.edu",
    "name": "The Association for International Students of Law (AISL) aims to connect international students in t",
    "school": "USC Gould School of Law",
    "program": "Student Organization"
  },
  {
    "email": "apalsa@lawmail.usc.edu",
    "name": "The Asian Pacific American Law Students Association promotes equality and social progress for Asian ",
    "school": "USC Gould School of Law",
    "program": "Student Organization"
  },
  {
    "email": "pilf@lawmail.usc.edu",
    "name": "Visit Website",
    "school": "USC Gould School of Law",
    "program": "Student Organization"
  },
  {
    "email": "blsa@lawmail.usc.edu",
    "name": "The Black Law Students Association provides guidance, assistance and support academically, professio",
    "school": "USC Gould School of Law",
    "program": "Student Organization"
  },
  {
    "email": "bld@lawmail.usc.edu",
    "name": "The Business Law Digest (BLD) is a business law practice journal that provides advice on current iss",
    "school": "USC Gould School of Law",
    "program": "Student Organization"
  },
  {
    "email": "bls@lawmail.usc.edu",
    "name": "The Business Law Society enhances students' practical knowledge and skills in commercial transaction",
    "school": "USC Gould School of Law",
    "program": "Student Organization"
  },
  {
    "email": "csihen@lawmail.usc.edu",
    "name": "The C-Suite and In-House Executive Network recognizes that the legal profession extends beyond the b",
    "school": "USC Gould School of Law",
    "program": "Student Organization"
  },
  {
    "email": "cannabislawsociety@lawmail.usc.edu",
    "name": "The purpose of Cannabis Law Society is to educate students and foster discussions on current legal i",
    "school": "USC Gould School of Law",
    "program": "Student Organization"
  },
  {
    "email": "clsaa@lawmail.usc.edu",
    "name": "The Chinese Law Student Alumni Association (CLSAA) seeks to explore the academic and career issues r",
    "school": "USC Gould School of Law",
    "program": "Student Organization"
  },
  {
    "email": "caps_usc@lawmail.usc.edu",
    "name": "Do you know what's on your credit report? Many people don't! Credit report, consumer debt and studen",
    "school": "USC Gould School of Law",
    "program": "Student Organization"
  },
  {
    "email": "crimlawsociety@lawmail.usc.edu",
    "name": "The Criminal Law Society provides resources and opportunities to encourage students to better positi",
    "school": "USC Gould School of Law",
    "program": "Student Organization"
  },
  {
    "email": "eels@lawmail.usc.edu",
    "name": "The Energy & Environmental Law Society brings together students interested in environmental and ener",
    "school": "USC Gould School of Law",
    "program": "Student Organization"
  },
  {
    "email": "els@lawmail.usc.edu",
    "name": "The Entertainment Law Society helps prepare students for the wide range of legal careers within the ",
    "school": "USC Gould School of Law",
    "program": "Student Organization"
  },
  {
    "email": "fls@lawmail.usc.edu",
    "name": "Family Law Society",
    "school": "USC Gould School of Law",
    "program": "Student Organization"
  },
  {
    "email": "fbls@lawmail.usc.edu",
    "name": "The Fashion and Beauty Law Society connects the USC Gould community to the fashion and beauty indust",
    "school": "USC Gould School of Law",
    "program": "Student Organization"
  },
  {
    "email": "federalistsociety@lawmail.usc.edu",
    "name": "The Federalist Society for Law and Public Policy Studies unites conservatives and libertarians dedic",
    "school": "USC Gould School of Law",
    "program": "Student Organization"
  },
  {
    "email": "FGP@lawmail.usc.edu",
    "name": "The First Generation Professionals student organization seeks to provide community and resources for",
    "school": "USC Gould School of Law",
    "program": "Student Organization"
  },
  {
    "email": "artlawsociety@lawmail.usc.edu",
    "name": "GALS explores the effect of law on the expression, sale and exhibition of art, focusing on contempor",
    "school": "USC Gould School of Law",
    "program": "Student Organization"
  },
  {
    "email": "gcf@lawmail.usc.edu",
    "name": "Gould Christian Fellowship (GCF) seeks to provide a spiritual home for students at the law school an",
    "school": "USC Gould School of Law",
    "program": "Student Organization"
  },
  {
    "email": "gdrs@lawmail.usc.edu",
    "name": "The Gould Dispute Resolution Society focuses on creating and promoting educational and practical opp",
    "school": "USC Gould School of Law",
    "program": "Student Organization"
  },
  {
    "email": "gps@lawmail.usc.edu",
    "name": "Gould Philosophy Society",
    "school": "USC Gould School of Law",
    "program": "Student Organization"
  },
  {
    "email": "healthlawsociety@lawmail.usc.edu",
    "name": "The Health Law Society aims to raise awareness of what this area of the law encompasses as well as t",
    "school": "USC Gould School of Law",
    "program": "Student Organization"
  },
  {
    "email": "iptech@lawmail.usc.edu",
    "name": "The Society addresses all facets of intellectual property law and the rapid changes in technology dr",
    "school": "USC Gould School of Law",
    "program": "Student Organization"
  },
  {
    "email": "ilro@lawmail.usc.edu",
    "name": "The group advances student pursuits and interests in international law and relations by promoting un",
    "school": "USC Gould School of Law",
    "program": "Student Organization"
  },
  {
    "email": "irap@lawmail.usc.edu",
    "name": "The International Refugee Assistance Project helps refugees escape harm and persecution by providing",
    "school": "USC Gould School of Law",
    "program": "Student Organization"
  },
  {
    "email": "ilsa@lawmail.usc.edu",
    "name": "USC's ILSA strives to promote the interests of Persian/Iranian students on campus and throughout the",
    "school": "USC Gould School of Law",
    "program": "Student Organization"
  },
  {
    "email": "janebolinproject@lawmail.usc.edu",
    "name": "The Jane Bolin Project is a student-led diversity initiative. We are running a campaign for equality",
    "school": "USC Gould School of Law",
    "program": "Student Organization"
  },
  {
    "email": "jlsa@lawmail.usc.edu",
    "name": "The Jewish Law Students Association fosters involvement in the Jewish community at USC and in Los An",
    "school": "USC Gould School of Law",
    "program": "Student Organization"
  },
  {
    "email": "llsa@lawmail.usc.edu",
    "name": "The Latinx Law Students Association provides academic support, scholarships and community service op",
    "school": "USC Gould School of Law",
    "program": "Student Organization"
  },
  {
    "email": "lsbh@lawmail.usc.edu",
    "name": "LSBH is dedicated to supporting students' mental health and wellness needs. We provide perspective a",
    "school": "USC Gould School of Law",
    "program": "Student Organization"
  },
  {
    "email": "laab@lawmail.usc.edu",
    "name": "Established in the wake of Hurricane Katrina, Legal Aid Alternative Break enables students to build ",
    "school": "USC Gould School of Law",
    "program": "Student Organization"
  },
  {
    "email": "menalsa@lawmail.usc.edu",
    "name": "The Middle Eastern and North African Law Student Association promotes equality and social progress f",
    "school": "USC Gould School of Law",
    "program": "Student Organization"
  },
  {
    "email": "mls@lawmail.usc.edu",
    "name": "The Music Law Society aims to expose students interested in music and entertainment law to the gamut",
    "school": "USC Gould School of Law",
    "program": "Student Organization"
  },
  {
    "email": "nlg@lawmail.usc.edu",
    "name": "Through the USC student chapter of the National Lawyers Guild, members promote public interest lawye",
    "school": "USC Gould School of Law",
    "program": "Student Organization"
  },
  {
    "email": "nallsa@lawmail.usc.edu",
    "name": "The purpose of the Native American Law & Law Students Association is to support the advancement of i",
    "school": "USC Gould School of Law",
    "program": "Student Organization"
  },
  {
    "email": "outlaw@lawmail.usc.edu",
    "name": "Outlaw promotes equality, social progress, and the interests of gay, lesbian, bisexual, trans, inter",
    "school": "USC Gould School of Law",
    "program": "Student Organization"
  },
  {
    "email": "owls@lawmail.usc.edu",
    "name": "OWLS provides a community at Gould for those who self-identify as a non-traditional student. Whether",
    "school": "USC Gould School of Law",
    "program": "Student Organization"
  },
  {
    "email": "pad@lawmail.usc.edu",
    "name": "The preeminent law fraternity, Phi Alpha Delta advances integrity, compassion and courage through se",
    "school": "USC Gould School of Law",
    "program": "Student Organization"
  },
  {
    "email": "pcls@lawmail.usc.edu",
    "name": "The Privacy and Cybersecurity Law Society informs students about privacy law and cybersecurity and r",
    "school": "USC Gould School of Law",
    "program": "Student Organization"
  },
  {
    "email": "rels@lawmail.usc.edu",
    "name": "The Real Estate Law Society offers social, networking and professional development events that expos",
    "school": "USC Gould School of Law",
    "program": "Student Organization"
  },
  {
    "email": "salsa@lawmail.usc.edu",
    "name": "South Asian Law Student Association (SALSA) is dedicated to creating a supportive community among st",
    "school": "USC Gould School of Law",
    "program": "Student Organization"
  },
  {
    "email": "sportslawsociety@lawmail.usc.edu",
    "name": "The Sports Law Society hosts events featuring sports law professionals, helps identify career opport",
    "school": "USC Gould School of Law",
    "program": "Student Organization"
  },
  {
    "email": "streetlaw@lawmail.usc.edu",
    "name": "Street Law enables members to share the law's importance with others by developing an ethic of commu",
    "school": "USC Gould School of Law",
    "program": "Student Organization"
  },
  {
    "email": "saldf@lawmail.usc.edu",
    "name": "The Student Animal Legal Defense Fund (SALDF) at the USC Gould School of Law is devoted to enhancing",
    "school": "USC Gould School of Law",
    "program": "Student Organization"
  },
  {
    "email": "wla@lawmail.usc.edu",
    "name": "The Women's Law Association supports the advancement of women in the legal community and society at ",
    "school": "USC Gould School of Law",
    "program": "Student Organization"
  },
  {
    "email": "wocc@lawmail.usc.edu",
    "name": "The Womxn (the x is intentional) of Color Collective (WOCC) is a student organization that provides ",
    "school": "USC Gould School of Law",
    "program": "Student Organization"
  },
  {
    "email": "VCTA@lawmail.usc.edu",
    "name": "Joining the Venture Capital and Technology Association (VCTA) at USC Gould School of Law means becom",
    "school": "USC Gould School of Law",
    "program": "Student Organization"
  },
  {
    "email": "jiarenas@usc.edu",
    "name": "Jorge Arenas",
    "school": "USC Dornsife - Department of Economics",
    "program": "PhD in Economics"
  },
  {
    "email": "cpbarnes@usc.edu",
    "name": "Carsten Barnes",
    "school": "USC Dornsife - Department of Economics",
    "program": "PhD in Economics"
  },
  {
    "email": "dadesai@usc.edu",
    "name": "Deven Desai",
    "school": "USC Dornsife - Department of Economics",
    "program": "PhD in Economics"
  },
  {
    "email": "jialun@usc.edu",
    "name": "Jialun \"Neil\" He",
    "school": "USC Dornsife - Department of Economics",
    "program": "PhD in Economics"
  },
  {
    "email": "ishikuro@usc.edu",
    "name": "Yuto Ishikuro",
    "school": "USC Dornsife - Department of Economics",
    "program": "PhD in Economics"
  },
  {
    "email": "mirasyed@usc.edu",
    "name": "Hasan Mirasyedi",
    "school": "USC Dornsife - Department of Economics",
    "program": "PhD in Economics"
  },
  {
    "email": "ipopov@usc.edu",
    "name": "Ivan Popov",
    "school": "USC Dornsife - Department of Economics",
    "program": "PhD in Economics"
  },
  {
    "email": "porrasba@usc.edu",
    "name": "Maryan Raquel Porras Barrera",
    "school": "USC Dornsife - Department of Economics",
    "program": "PhD in Economics"
  },
  {
    "email": "setyonug@usc.edu",
    "name": "Dimas Setyonugroho",
    "school": "USC Dornsife - Department of Economics",
    "program": "PhD in Economics"
  },
  {
    "email": "hyang705@usc.edu",
    "name": "Hao Yang",
    "school": "USC Dornsife - Department of Economics",
    "program": "PhD in Economics"
  },
  {
    "email": "bzhang45@usc.edu",
    "name": "Boyang Zhang",
    "school": "USC Dornsife - Department of Economics",
    "program": "PhD in Economics"
  },
  {
    "email": "tianqiz5@usc.edu",
    "name": "Tianqi Zhang",
    "school": "USC Dornsife - Department of Economics",
    "program": "PhD in Economics"
  },
  {
    "email": "adzheng@usc.edu",
    "name": "Aaron Zheng",
    "school": "USC Dornsife - Department of Economics",
    "program": "PhD in Economics"
  },
  {
    "email": "pcaetano@usc.edu",
    "name": "Patricia Caetano",
    "school": "USC Dornsife - Department of Economics",
    "program": "PhD in Economics"
  },
  {
    "email": "fossi@usc.edu",
    "name": "Matteo Fossi",
    "school": "USC Dornsife - Department of Economics",
    "program": "PhD in Economics"
  },
  {
    "email": "shuaiyuj@usc.edu",
    "name": "Shuaiyu Jiang",
    "school": "USC Dornsife - Department of Economics",
    "program": "PhD in Economics"
  },
  {
    "email": "kehuilen@usc.edu",
    "name": "Kehui \"Chris\" Leng",
    "school": "USC Dornsife - Department of Economics",
    "program": "PhD in Economics"
  },
  {
    "email": "jinlinli@usc.edu",
    "name": "Jinlin Li",
    "school": "USC Dornsife - Department of Economics",
    "program": "PhD in Economics"
  },
  {
    "email": "changfen@usc.edu",
    "name": "Changfeng Liu",
    "school": "USC Dornsife - Department of Economics",
    "program": "PhD in Economics"
  },
  {
    "email": "onyechi@usc.edu",
    "name": "Odera Onyechi",
    "school": "USC Dornsife - Department of Economics",
    "program": "PhD in Economics"
  },
  {
    "email": "jeonggil@usc.edu",
    "name": "Jeonggil Song",
    "school": "USC Dornsife - Department of Economics",
    "program": "PhD in Economics"
  },
  {
    "email": "rensu@usc.edu",
    "name": "Ren Su",
    "school": "USC Dornsife - Department of Economics",
    "program": "PhD in Economics"
  },
  {
    "email": "xuemengy@usc.edu",
    "name": "Xuemeng Yin",
    "school": "USC Dornsife - Department of Economics",
    "program": "PhD in Economics"
  },
  {
    "email": "hamzahah@usc.edu",
    "name": "Hamzah Ahmed",
    "school": "USC Dornsife - Department of Economics",
    "program": "PhD in Economics"
  },
  {
    "email": "priyac@usc.edu",
    "name": "Priya Chaturvedi",
    "school": "USC Dornsife - Department of Economics",
    "program": "PhD in Economics"
  },
  {
    "email": "juanbgon@usc.edu",
    "name": "Juan Gonzalez",
    "school": "USC Dornsife - Department of Economics",
    "program": "PhD in Economics"
  },
  {
    "email": "dkang255@usc.edu",
    "name": "Dong Hyeok Kang",
    "school": "USC Dornsife - Department of Economics",
    "program": "PhD in Economics"
  },
  {
    "email": "jylevy@usc.edu",
    "name": "Joshua Levy",
    "school": "USC Dornsife - Department of Economics",
    "program": "PhD in Economics"
  },
  {
    "email": "hliu9506@usc.edu",
    "name": "Hang Liu",
    "school": "USC Dornsife - Department of Economics",
    "program": "PhD in Economics"
  },
  {
    "email": "zliu1600@usc.edu",
    "name": "Zhihan Liu",
    "school": "USC Dornsife - Department of Economics",
    "program": "PhD in Economics"
  },
  {
    "email": "kesharsh@usc.edu",
    "name": "Keshar Shahi",
    "school": "USC Dornsife - Department of Economics",
    "program": "PhD in Economics"
  },
  {
    "email": "ssharma9@usc.edu",
    "name": "Sankalp Sharma",
    "school": "USC Dornsife - Department of Economics",
    "program": "PhD in Economics"
  },
  {
    "email": "siqisu@usc.edu",
    "name": "Siqi Su",
    "school": "USC Dornsife - Department of Economics",
    "program": "PhD in Economics"
  },
  {
    "email": "akashtha@usc.edu",
    "name": "Akash Thakkar",
    "school": "USC Dornsife - Department of Economics",
    "program": "PhD in Economics"
  },
  {
    "email": "ywang809@usc.edu",
    "name": "Yifei Wang",
    "school": "USC Dornsife - Department of Economics",
    "program": "PhD in Economics"
  },
  {
    "email": "yizhongw@usc.edu",
    "name": "Yizhong Wang",
    "school": "USC Dornsife - Department of Economics",
    "program": "PhD in Economics"
  },
  {
    "email": "yujuew@usc.edu",
    "name": "Yujue Wang",
    "school": "USC Dornsife - Department of Economics",
    "program": "PhD in Economics"
  },
  {
    "email": "dingfanz@usc.edu",
    "name": "Dingfan Zhang",
    "school": "USC Dornsife - Department of Economics",
    "program": "PhD in Economics"
  },
  {
    "email": "jingshuc@usc.edu",
    "name": "Jingshu Chen",
    "school": "USC Dornsife - Department of Economics",
    "program": "PhD in Economics"
  },
  {
    "email": "pcoster@usc.edu",
    "name": "Pierre Coster",
    "school": "USC Dornsife - Department of Economics",
    "program": "PhD in Economics"
  },
  {
    "email": "defarias@usc.edu",
    "name": "Alison De Farias",
    "school": "USC Dornsife - Department of Economics",
    "program": "PhD in Economics"
  },
  {
    "email": "sd59576@usc.edu",
    "name": "Santiago De Martini",
    "school": "USC Dornsife - Department of Economics",
    "program": "PhD in Economics"
  },
  {
    "email": "jcduggan@usc.edu",
    "name": "Julian Duggan",
    "school": "USC Dornsife - Department of Economics",
    "program": "PhD in Economics"
  },
  {
    "email": "jironghe@usc.edu",
    "name": "Jirong He",
    "school": "USC Dornsife - Department of Economics",
    "program": "PhD in Economics"
  },
  {
    "email": "rivanov@usc.edu",
    "name": "Radostin Ivanov",
    "school": "USC Dornsife - Department of Economics",
    "program": "PhD in Economics"
  },
  {
    "email": "junhapar@usc.edu",
    "name": "Junha Park",
    "school": "USC Dornsife - Department of Economics",
    "program": "PhD in Economics"
  },
  {
    "email": "arujshuk@usc.edu",
    "name": "Aruj Shukla",
    "school": "USC Dornsife - Department of Economics",
    "program": "PhD in Economics"
  },
  {
    "email": "salonita@usc.edu",
    "name": "Saloni Taneja",
    "school": "USC Dornsife - Department of Economics",
    "program": "PhD in Economics"
  },
  {
    "email": "ignaciot@usc.edu",
    "name": "Ignacio Torres",
    "school": "USC Dornsife - Department of Economics",
    "program": "PhD in Economics"
  },
  {
    "email": "wxuan@usc.edu",
    "name": "Wei Xuan",
    "school": "USC Dornsife - Department of Economics",
    "program": "PhD in Economics"
  },
  {
    "email": "haizhou@usc.edu",
    "name": "Hai Zhou",
    "school": "USC Dornsife - Department of Economics",
    "program": "PhD in Economics"
  },
  {
    "email": "sijiac@usc.edu",
    "name": "Sijia Chen",
    "school": "USC Dornsife - Department of Economics",
    "program": "PhD in Economics"
  },
  {
    "email": "yugenche@usc.edu",
    "name": "Yugen Chen",
    "school": "USC Dornsife - Department of Economics",
    "program": "PhD in Economics"
  },
  {
    "email": "delatte@usc.edu",
    "name": "Paul Delatte",
    "school": "USC Dornsife - Department of Economics",
    "program": "PhD in Economics"
  },
  {
    "email": "fotedar@usc.edu",
    "name": "Vanshika Fotedar",
    "school": "USC Dornsife - Department of Economics",
    "program": "PhD in Economics"
  },
  {
    "email": "woojinki@usc.edu",
    "name": "Woo-Jin Kim",
    "school": "USC Dornsife - Department of Economics",
    "program": "PhD in Economics"
  },
  {
    "email": "nlangsto@usc.edu",
    "name": "Nick Langston",
    "school": "USC Dornsife - Department of Economics",
    "program": "PhD in Economics"
  },
  {
    "email": "lofaso@usc.edu",
    "name": "Marco Lo Faso",
    "school": "USC Dornsife - Department of Economics",
    "program": "PhD in Economics"
  },
  {
    "email": "ozyerkoc@usc.edu",
    "name": "Serap Inci Ozyer Koca",
    "school": "USC Dornsife - Department of Economics",
    "program": "PhD in Economics"
  },
  {
    "email": "mpaetow@usc.edu",
    "name": "Mychaela Paetow",
    "school": "USC Dornsife - Department of Economics",
    "program": "PhD in Economics"
  },
  {
    "email": "pinillos@usc.edu",
    "name": "Juliana Pinillos Perdomo",
    "school": "USC Dornsife - Department of Economics",
    "program": "PhD in Economics"
  },
  {
    "email": "haoxuans@usc.edu",
    "name": "Haoxuan \"Jerry\" Shen",
    "school": "USC Dornsife - Department of Economics",
    "program": "PhD in Economics"
  },
  {
    "email": "sherstne@usc.edu",
    "name": "Daniil \"Daniel\" Sherstnev",
    "school": "USC Dornsife - Department of Economics",
    "program": "PhD in Economics"
  },
  {
    "email": "saizhang@usc.edu",
    "name": "Sai Zhang",
    "school": "USC Dornsife - Department of Economics",
    "program": "PhD in Economics"
  },
  {
    "email": "bech@usc.edu",
    "name": "Andreas Bech",
    "school": "USC Dornsife - Department of Economics",
    "program": "PhD in Economics"
  },
  {
    "email": "shreyab@usc.edu",
    "name": "Shreya Bhardwaj",
    "school": "USC Dornsife - Department of Economics",
    "program": "PhD in Economics"
  },
  {
    "email": "matthecb@usc.edu",
    "name": "Matthew Burr",
    "school": "USC Dornsife - Department of Economics",
    "program": "PhD in Economics"
  },
  {
    "email": "minsooch@usc.edu",
    "name": "Minsoo Cho",
    "school": "USC Dornsife - Department of Economics",
    "program": "PhD in Economics"
  },
  {
    "email": "godazand@usc.edu",
    "name": "Bardia Godazandeh",
    "school": "USC Dornsife - Department of Economics",
    "program": "PhD in Economics"
  },
  {
    "email": "koca@usc.edu",
    "name": "Yakup Kutsal Koca",
    "school": "USC Dornsife - Department of Economics",
    "program": "PhD in Economics"
  },
  {
    "email": "jingkong@usc.edu",
    "name": "Jing Kong",
    "school": "USC Dornsife - Department of Economics",
    "program": "PhD in Economics"
  },
  {
    "email": "minjikwa@usc.edu",
    "name": "Minji Kwak",
    "school": "USC Dornsife - Department of Economics",
    "program": "PhD in Economics"
  },
  {
    "email": "lichang@usc.edu",
    "name": "Chang Li",
    "school": "USC Dornsife - Department of Economics",
    "program": "PhD in Economics"
  },
  {
    "email": "wendama@usc.edu",
    "name": "Wenda Ma",
    "school": "USC Dornsife - Department of Economics",
    "program": "PhD in Economics"
  },
  {
    "email": "snimmaga@usc.edu",
    "name": "Sneha Nimmagadda",
    "school": "USC Dornsife - Department of Economics",
    "program": "PhD in Economics"
  },
  {
    "email": "jinseok@usc.edu",
    "name": "Jin Seok Park",
    "school": "USC Dornsife - Department of Economics",
    "program": "PhD in Economics"
  },
  {
    "email": "ziliyang@usc.edu",
    "name": "Zili Yang",
    "school": "USC Dornsife - Department of Economics",
    "program": "PhD in Economics"
  },
  {
    "email": "yuzhengy@usc.edu",
    "name": "Isaac Yu",
    "school": "USC Dornsife - Department of Economics",
    "program": "PhD in Economics"
  },
  {
    "email": "xiaoxin@usc.edu",
    "name": "Xiaoxin Zhang",
    "school": "USC Dornsife - Department of Economics",
    "program": "PhD in Economics"
  },
  {
    "email": "gabato@usc.edu",
    "name": "Gabby Abato",
    "school": "USC Dornsife - Department of Mathematics",
    "program": "PhD in Mathematics"
  },
  {
    "email": "oafifi@usc.edu",
    "name": "Omar Afifi",
    "school": "USC Dornsife - Department of Mathematics",
    "program": "PhD in Mathematics"
  },
  {
    "email": "ahsanull@usc.edu",
    "name": "Yusuf Ahsanullah",
    "school": "USC Dornsife - Department of Mathematics",
    "program": "PhD in Mathematics"
  },
  {
    "email": "aksay@usc.edu",
    "name": "Metehan Aksay",
    "school": "USC Dornsife - Department of Mathematics",
    "program": "PhD in Mathematics"
  },
  {
    "email": "arcona@usc.edu",
    "name": "Dominic Arcona",
    "school": "USC Dornsife - Department of Mathematics",
    "program": "PhD in Mathematics"
  },
  {
    "email": "maydin@usc.edu",
    "name": "Mustafa Aydin",
    "school": "USC Dornsife - Department of Mathematics",
    "program": "PhD in Mathematics"
  },
  {
    "email": "ebucci@usc.edu",
    "name": "Elisa Bucci",
    "school": "USC Dornsife - Department of Mathematics",
    "program": "PhD in Mathematics"
  },
  {
    "email": "caohan@usc.edu",
    "name": "Han Cao",
    "school": "USC Dornsife - Department of Mathematics",
    "program": "PhD in Mathematics"
  },
  {
    "email": "bcetin@usc.edu",
    "name": "Baran Cetin",
    "school": "USC Dornsife - Department of Mathematics",
    "program": "PhD in Mathematics"
  },
  {
    "email": "cachang@usc.edu",
    "name": "Chris Chang",
    "school": "USC Dornsife - Department of Mathematics",
    "program": "PhD in Mathematics"
  },
  {
    "email": "chlachid@usc.edu",
    "name": "Ellen Chlachidze",
    "school": "USC Dornsife - Department of Mathematics",
    "program": "PhD in Mathematics"
  },
  {
    "email": "ajclay@usc.edu",
    "name": "Alexander Clay",
    "school": "USC Dornsife - Department of Mathematics",
    "program": "PhD in Mathematics"
  },
  {
    "email": "lcyr@usc.edu",
    "name": "Louis-Simon Cyr",
    "school": "USC Dornsife - Department of Mathematics",
    "program": "PhD in Mathematics"
  },
  {
    "email": "fdesousa@usc.edu",
    "name": "Farhad De Sousa",
    "school": "USC Dornsife - Department of Mathematics",
    "program": "PhD in Mathematics"
  },
  {
    "email": "dfdiaz@usc.edu",
    "name": "Diego Diaz",
    "school": "USC Dornsife - Department of Mathematics",
    "program": "PhD in Mathematics"
  },
  {
    "email": "rundongd@usc.edu",
    "name": "Rundong Ding",
    "school": "USC Dornsife - Department of Mathematics",
    "program": "PhD in Mathematics"
  },
  {
    "email": "telling@usc.edu",
    "name": "Tycho Elling",
    "school": "USC Dornsife - Department of Mathematics",
    "program": "PhD in Mathematics"
  },
  {
    "email": "brianfan@usc.edu",
    "name": "Yunjie (Brian) Fan",
    "school": "USC Dornsife - Department of Mathematics",
    "program": "PhD in Mathematics"
  },
  {
    "email": "ifeng@usc.edu",
    "name": "Ivan Feng",
    "school": "USC Dornsife - Department of Mathematics",
    "program": "PhD in Mathematics"
  },
  {
    "email": "alexfu.math@usc.edu",
    "name": "Alexander Fu",
    "school": "USC Dornsife - Department of Mathematics",
    "program": "PhD in Mathematics"
  },
  {
    "email": "frankgao@usc.edu",
    "name": "Linshan (Frank) Gao",
    "school": "USC Dornsife - Department of Mathematics",
    "program": "PhD in Mathematics"
  },
  {
    "email": "bgillen@usc.edu",
    "name": "Benjamin Gillen",
    "school": "USC Dornsife - Department of Mathematics",
    "program": "PhD in Mathematics"
  },
  {
    "email": "girshfel@usc.edu",
    "name": "Inga Girshfeld",
    "school": "USC Dornsife - Department of Mathematics",
    "program": "PhD in Mathematics"
  },
  {
    "email": "grlj@usc.edu",
    "name": "Jernej Grlj",
    "school": "USC Dornsife - Department of Mathematics",
    "program": "PhD in Mathematics"
  },
  {
    "email": "zkiss@usc.edu",
    "name": "Zsombor Kiss",
    "school": "USC Dornsife - Department of Mathematics",
    "program": "PhD in Mathematics"
  },
  {
    "email": "ligu@usc.edu",
    "name": "Li Gu",
    "school": "USC Dornsife - Department of Mathematics",
    "program": "PhD in Mathematics"
  },
  {
    "email": "zihaogu@usc.edu",
    "name": "Zihao Gu",
    "school": "USC Dornsife - Department of Mathematics",
    "program": "PhD in Mathematics"
  },
  {
    "email": "lhakobya@usc.edu",
    "name": "Levon Hakobyan",
    "school": "USC Dornsife - Department of Mathematics",
    "program": "PhD in Mathematics"
  },
  {
    "email": "boxihao@usc.edu",
    "name": "Boxi Hao",
    "school": "USC Dornsife - Department of Mathematics",
    "program": "PhD in Mathematics"
  },
  {
    "email": "hchewitt@usc.edu",
    "name": "Hunter Hewitt",
    "school": "USC Dornsife - Department of Mathematics",
    "program": "PhD in Mathematics"
  },
  {
    "email": "mshuang@usc.edu",
    "name": "Michael Huang",
    "school": "USC Dornsife - Department of Mathematics",
    "program": "PhD in Mathematics"
  },
  {
    "email": "ingimars@usc.edu",
    "name": "Benjamin Ingimarson",
    "school": "USC Dornsife - Department of Mathematics",
    "program": "PhD in Mathematics"
  },
  {
    "email": "nkaramya@usc.edu",
    "name": "Nicholas Karamyan",
    "school": "USC Dornsife - Department of Mathematics",
    "program": "PhD in Mathematics"
  },
  {
    "email": "skim2261@usc.edu",
    "name": "Sung Hyun Kim",
    "school": "USC Dornsife - Department of Mathematics",
    "program": "PhD in Mathematics"
  },
  {
    "email": "pengtaol@usc.edu",
    "name": "Pengtao Li",
    "school": "USC Dornsife - Department of Mathematics",
    "program": "PhD in Mathematics"
  },
  {
    "email": "jiaqil@usc.edu",
    "name": "Jiaqi Liu",
    "school": "USC Dornsife - Department of Mathematics",
    "program": "PhD in Mathematics"
  },
  {
    "email": "tianleli@usc.edu",
    "name": "Tianle Liu",
    "school": "USC Dornsife - Department of Mathematics",
    "program": "PhD in Mathematics"
  },
  {
    "email": "davidoco@usc.edu",
    "name": "David O’Connor",
    "school": "USC Dornsife - Department of Mathematics",
    "program": "PhD in Mathematics"
  },
  {
    "email": "yijiepan@usc.edu",
    "name": "Yijie Pan",
    "school": "USC Dornsife - Department of Mathematics",
    "program": "PhD in Mathematics"
  },
  {
    "email": "dylanpar@usc.edu",
    "name": "Dylan Park",
    "school": "USC Dornsife - Department of Mathematics",
    "program": "PhD in Mathematics"
  },
  {
    "email": "pishkoo@usc.edu",
    "name": "Reza Pishkoo",
    "school": "USC Dornsife - Department of Mathematics",
    "program": "PhD in Mathematics"
  },
  {
    "email": "bqiao@usc.edu",
    "name": "Bixing Qiao",
    "school": "USC Dornsife - Department of Mathematics",
    "program": "PhD in Mathematics"
  },
  {
    "email": "vladroma@usc.edu",
    "name": "Vlad Roman",
    "school": "USC Dornsife - Department of Mathematics",
    "program": "PhD in Mathematics"
  },
  {
    "email": "zijianro@usc.edu",
    "name": "Zijian Rong",
    "school": "USC Dornsife - Department of Mathematics",
    "program": "PhD in Mathematics"
  },
  {
    "email": "sajan@usc.edu",
    "name": "Anna Mary Sajan",
    "school": "USC Dornsife - Department of Mathematics",
    "program": "PhD in Mathematics"
  },
  {
    "email": "sionit@usc.edu",
    "name": "Benjamin Sionit",
    "school": "USC Dornsife - Department of Mathematics",
    "program": "PhD in Mathematics"
  },
  {
    "email": "ysomaiya@usc.edu",
    "name": "Yash Somaiya",
    "school": "USC Dornsife - Department of Mathematics",
    "program": "PhD in Mathematics"
  },
  {
    "email": "tamur@usc.edu",
    "name": "Yahya Tamur",
    "school": "USC Dornsife - Department of Mathematics",
    "program": "PhD in Mathematics"
  },
  {
    "email": "qinyangt@usc.edu",
    "name": "Qinyang Tan",
    "school": "USC Dornsife - Department of Mathematics",
    "program": "PhD in Mathematics"
  },
  {
    "email": "yntao@usc.edu",
    "name": "Yuxuan (Troy) Tao",
    "school": "USC Dornsife - Department of Mathematics",
    "program": "PhD in Mathematics"
  },
  {
    "email": "uluatam@usc.edu",
    "name": "Sophie Uluatam",
    "school": "USC Dornsife - Department of Mathematics",
    "program": "PhD in Mathematics"
  },
  {
    "email": "bingyuan@usc.edu",
    "name": "Bingyuan Wang",
    "school": "USC Dornsife - Department of Mathematics",
    "program": "PhD in Mathematics"
  },
  {
    "email": "gaozhanw@usc.edu",
    "name": "Gaozhan Wang",
    "school": "USC Dornsife - Department of Mathematics",
    "program": "PhD in Mathematics"
  },
  {
    "email": "jwang535@usc.edu",
    "name": "Jiawei Wang",
    "school": "USC Dornsife - Department of Mathematics",
    "program": "PhD in Mathematics"
  },
  {
    "email": "qiminw@usc.edu",
    "name": "Qimin Wang",
    "school": "USC Dornsife - Department of Mathematics",
    "program": "PhD in Mathematics"
  },
  {
    "email": "jiayiwen@usc.edu",
    "name": "Jiayi Wen",
    "school": "USC Dornsife - Department of Mathematics",
    "program": "PhD in Mathematics"
  },
  {
    "email": "haosenwu@usc.edu",
    "name": "Haosen Wu",
    "school": "USC Dornsife - Department of Mathematics",
    "program": "PhD in Mathematics"
  },
  {
    "email": "lx_375@usc.edu",
    "name": "Longhui Xu",
    "school": "USC Dornsife - Department of Mathematics",
    "program": "PhD in Mathematics"
  },
  {
    "email": "xuqi@usc.edu",
    "name": "Qi Xu",
    "school": "USC Dornsife - Department of Mathematics",
    "program": "PhD in Mathematics"
  },
  {
    "email": "fyang399@usc.edu",
    "name": "Fan Yang",
    "school": "USC Dornsife - Department of Mathematics",
    "program": "PhD in Mathematics"
  },
  {
    "email": "qiyuzhan@usc.edu",
    "name": "Qiyu Zhang",
    "school": "USC Dornsife - Department of Mathematics",
    "program": "PhD in Mathematics"
  },
  {
    "email": "wzhang49@usc.edu",
    "name": "Wenhao Zhang",
    "school": "USC Dornsife - Department of Mathematics",
    "program": "PhD in Mathematics"
  },
  {
    "email": "ruoyuzhe@usc.edu",
    "name": "Ruoyu Zheng",
    "school": "USC Dornsife - Department of Mathematics",
    "program": "PhD in Mathematics"
  },
  {
    "email": "yzhou602@usc.edu",
    "name": "Yuantao Zhou",
    "school": "USC Dornsife - Department of Mathematics",
    "program": "PhD in Mathematics"
  },
  {
    "email": "zzhou108@usc.edu",
    "name": "Zixiang Zhou",
    "school": "USC Dornsife - Department of Mathematics",
    "program": "PhD in Mathematics"
  },
  {
    "email": "wantongz@usc.edu",
    "name": "Wantong (Sabrina) Zhu",
    "school": "USC Dornsife - Department of Mathematics",
    "program": "PhD in Mathematics"
  }
]